synthetic_data_gen/__init__.py
synthetic_data_gen/data_generation.py
synthetic_data_gen/dataset_mixer.py
synthetic_data_gen/extract.py
synthetic_data_gen/extract_labelme_from_folder.py
synthetic_data_gen/extract_to_yolo.py
synthetic_data_gen/show_images_with_bboxes.py
synthetic_data_gen/data/default_augmentation.yml
synthetic_data_gen-0.1.4.dist-info/licenses/LICENSE
synthetic_data_gen-0.1.4.dist-info/METADATA
synthetic_data_gen-0.1.4.dist-info/WHEEL
synthetic_data_gen-0.1.4.dist-info/entry_points.txt
synthetic_data_gen-0.1.4.dist-info/top_level.txt
synthetic_data_gen-0.1.4.dist-info/RECORD
