Metadata-Version: 2.4
Name: synthetic_data_gen
Version: 0.1.4
Summary: A package for generating synthetic data, using labelme and generating synthetic images.
Author-email: Sebastian Jörz <seppel8426@gmail.com>
License: MIT License
License-File: LICENSE
Requires-Dist: kaggle
Requires-Dist: torch
Requires-Dist: torchvision
Requires-Dist: ultralytics
Requires-Dist: shapely
Requires-Dist: scikit-image
Requires-Dist: albumentations
Requires-Dist: joblib
Requires-Dist: labelme
Dynamic: license-file
